yoga_image_optimizer/__init__.py
yoga_image_optimizer/__main__.py
yoga_image_optimizer/about_dialog.py
yoga_image_optimizer/application.py
yoga_image_optimizer/config.py
yoga_image_optimizer/custom_pattern_dialog.py
yoga_image_optimizer/data_helpers.py
yoga_image_optimizer/file_chooser.py
yoga_image_optimizer/gtk_themes_helpers.py
yoga_image_optimizer/helpers.py
yoga_image_optimizer/image_formats.py
yoga_image_optimizer/image_store.py
yoga_image_optimizer/main_window.py
yoga_image_optimizer/settings_window.py
yoga_image_optimizer/stoppable_process_pool_executor.py
yoga_image_optimizer/thumbnailer.py
yoga_image_optimizer/translation.py
yoga_image_optimizer/data/images/icon.svg
yoga_image_optimizer/data/images/icon_128.png
yoga_image_optimizer/data/images/icon_256.png
yoga_image_optimizer/data/images/icon_32.png
yoga_image_optimizer/data/images/icon_64.png
yoga_image_optimizer/data/images/thumbnail_broken.svg
yoga_image_optimizer/data/images/thumbnail_inprogress.svg
yoga_image_optimizer/data/locales/de/LC_MESSAGES/org.flozz.yoga-image-optimizer.mo
yoga_image_optimizer/data/locales/es/LC_MESSAGES/org.flozz.yoga-image-optimizer.mo
yoga_image_optimizer/data/locales/fr/LC_MESSAGES/org.flozz.yoga-image-optimizer.mo
yoga_image_optimizer/data/locales/it/LC_MESSAGES/org.flozz.yoga-image-optimizer.mo
yoga_image_optimizer/data/locales/nl/LC_MESSAGES/org.flozz.yoga-image-optimizer.mo
yoga_image_optimizer/data/locales/oc/LC_MESSAGES/org.flozz.yoga-image-optimizer.mo
yoga_image_optimizer/data/locales/pt_BR/LC_MESSAGES/org.flozz.yoga-image-optimizer.mo
yoga_image_optimizer/data/locales/ru/LC_MESSAGES/org.flozz.yoga-image-optimizer.mo
yoga_image_optimizer/data/locales/tr/LC_MESSAGES/org.flozz.yoga-image-optimizer.mo
yoga_image_optimizer/data/style/yoga-image-optimizer.css
yoga_image_optimizer/data/ui/custom-pattern-dialog.glade
yoga_image_optimizer/data/ui/main-window.glade
yoga_image_optimizer/data/ui/settings-window.glade
yoga_image_optimizer-1.2.4.dist-info/COPYING
yoga_image_optimizer-1.2.4.dist-info/METADATA
yoga_image_optimizer-1.2.4.dist-info/WHEEL
yoga_image_optimizer-1.2.4.dist-info/entry_points.txt
yoga_image_optimizer-1.2.4.dist-info/top_level.txt
yoga_image_optimizer-1.2.4.dist-info/RECORD
