Metadata-Version: 2.1
Name: yoga_image_optimizer
Version: 1.2.4
Summary: A graphical interface to convert and optimize JPEG, PNG and WebP images (based on YOGA)
Home-page: https://yoga.flozz.org/
Author: Fabien LOISON
License: GPLv3
Project-URL: Source Code, https://github.com/flozz/yoga-image-optimizer
Project-URL: News, https://yoga.flozz.org/#news
Project-URL: Issues, https://github.com/flozz/yoga-image-optimizer/issues
Project-URL: Chat, https://discord.gg/P77sWhuSs4
Project-URL: Donate, https://github.com/flozz/yoga-image-optimizer#support-this-project
Keywords: image jpeg png optimizer converter guetzli zopfli gui gtk
License-File: COPYING
Requires-Dist: yoga >=1.1.0
Requires-Dist: pycairo
Requires-Dist: PyGObject >=3.26
Provides-Extra: dev
Requires-Dist: nox ; extra == 'dev'
Requires-Dist: flake8 ; extra == 'dev'
Requires-Dist: pytest ; extra == 'dev'
Requires-Dist: black ; extra == 'dev'
